waverunner/Server.py
waverunner/__init__.py
waverunner/__main__.py
waverunner-0.2b6.dist-info/METADATA
waverunner-0.2b6.dist-info/WHEEL
waverunner-0.2b6.dist-info/entry_points.txt
waverunner-0.2b6.dist-info/top_level.txt
waverunner-0.2b6.dist-info/RECORD
