Metadata-Version: 2.1
Name: waverunner
Version: 0.2b6
Summary: Package for sending (hardware) experiment requests across the network and receiving the results
Home-page: http://gitlab.com/bjmuld/waverunner/
Author: Barry Muldrey
Author-email: barry@muldrey.net
License: GPLv3
Project-URL: Bug Tracker, https://gitlab.com/bjmuld/waverunner/issues
Project-URL: Documentation, https://gitlab.com/bjmuld/waverunner
Keywords: scientific experiements analysis data management
Platform: UNKNOWN
Requires-Dist: netifaces
Requires-Dist: numpy
Requires-Dist: cloudpickle
Requires-Dist: dill
Requires-Dist: futures ; python_version == "2.7"
